.svnignore
README
bootstrap.py
buildout.cfg
setup.cfg
setup.py
simpleusage.tmproj
versions.cfg
docs/HISTORY.txt
docs/LICENSE.GPL
docs/LICENSE.txt
src/niteoweb/__init__.py
src/niteoweb.transmogrifier.simpleusage.egg-info/PKG-INFO
src/niteoweb.transmogrifier.simpleusage.egg-info/SOURCES.txt
src/niteoweb.transmogrifier.simpleusage.egg-info/dependency_links.txt
src/niteoweb.transmogrifier.simpleusage.egg-info/entry_points.txt
src/niteoweb.transmogrifier.simpleusage.egg-info/namespace_packages.txt
src/niteoweb.transmogrifier.simpleusage.egg-info/not-zip-safe
src/niteoweb.transmogrifier.simpleusage.egg-info/requires.txt
src/niteoweb.transmogrifier.simpleusage.egg-info/top_level.txt
src/niteoweb/transmogrifier/__init__.py
src/niteoweb/transmogrifier/simpleusage/__init__.py
src/niteoweb/transmogrifier/simpleusage/configure.zcml
src/niteoweb/transmogrifier/simpleusage/transmogrifier.cfg
src/niteoweb/transmogrifier/simpleusage/transmogrifier.py
src/niteoweb/transmogrifier/simpleusage/browser/__init__.py
src/niteoweb/transmogrifier/simpleusage/browser/configure.zcml
src/niteoweb/transmogrifier/simpleusage/browser/import.py