Metadata-Version: 1.0
Name: niteoweb.transmogrifier.simpleusage
Version: 1.0
Summary: A simple example of how to use collective.transmogrifier
Home-page: http://svn.plone.org/svn/collective/niteoweb.transmogrifier.simpleusage/
Author: NiteoWeb Ltd.
Author-email: info@niteoweb.com
License: GPL
Keywords: plone transmogrifier
Platform: UNKNOWN
Classifier: Framework :: Plone
Classifier: Programming Language :: Python
